ldf/__init__.py
ldf/audit.py
ldf/audit_api.py
ldf/cli.py
ldf/convert.py
ldf/coverage.py
ldf/detection.py
ldf/docs.py
ldf/doctor.py
ldf/hooks.py
ldf/init.py
ldf/lint.py
ldf/mcp_config.py
ldf/mcp_health.py
ldf/project_resolver.py
ldf/prompts.py
ldf/spec.py
ldf/spec_list.py
ldf/template.py
ldf/template_mgmt.py
ldf/update.py
ldf/_framework/descriptions.yaml
ldf/_framework/guardrails/README.md
ldf/_framework/guardrails/core.yaml
ldf/_framework/guardrails/presets/api-only.yaml
ldf/_framework/guardrails/presets/fintech.yaml
ldf/_framework/guardrails/presets/healthcare.yaml
ldf/_framework/guardrails/presets/saas.yaml
ldf/_framework/hooks/pre-commit.sh.j2
ldf/_framework/macros/clarify-first.md
ldf/_framework/macros/coverage-gate.md
ldf/_framework/macros/task-guardrails.md
ldf/_framework/question-packs/README.md
ldf/_framework/question-packs/core/api-design.yaml
ldf/_framework/question-packs/core/data-model.yaml
ldf/_framework/question-packs/core/security.yaml
ldf/_framework/question-packs/core/testing.yaml
ldf/_framework/question-packs/optional/billing.yaml
ldf/_framework/question-packs/optional/multi-tenancy.yaml
ldf/_framework/question-packs/optional/provisioning.yaml
ldf/_framework/question-packs/optional/webhooks.yaml
ldf/_framework/templates/design.md
ldf/_framework/templates/how-ldf-works.md
ldf/_framework/templates/requirements.md
ldf/_framework/templates/tasks.md
ldf/_mcp_servers/MCP_SETUP.md
ldf/_mcp_servers/coverage_reporter/README.md
ldf/_mcp_servers/coverage_reporter/coverage_parser.py
ldf/_mcp_servers/coverage_reporter/guardrail_validator.py
ldf/_mcp_servers/coverage_reporter/requirements.txt
ldf/_mcp_servers/coverage_reporter/server.py
ldf/_mcp_servers/db_inspector/README.md
ldf/_mcp_servers/db_inspector/template/requirements.txt
ldf/_mcp_servers/db_inspector/template/schema_query.py
ldf/_mcp_servers/db_inspector/template/server.py
ldf/_mcp_servers/spec_inspector/README.md
ldf/_mcp_servers/spec_inspector/guardrail_tracker.py
llm_ldf-1.2.0.dist-info/METADATA
llm_ldf-1.2.0.dist-info/WHEEL
llm_ldf-1.2.0.dist-info/entry_points.txt
llm_ldf-1.2.0.dist-info/licenses/LICENSE
llm_ldf-1.2.0.dist-info/RECORD
