Metadata-Version: 2.4
Name: llm-ldf
Version: 1.2.0
Summary: LLM Development Framework - Spec-driven development for AI-assisted engineering
Project-URL: Homepage, https://github.com/LLMdotInfo/ldf
Project-URL: Documentation, https://github.com/LLMdotInfo/ldf#readme
Project-URL: Repository, https://github.com/LLMdotInfo/ldf
Project-URL: Issues, https://github.com/LLMdotInfo/ldf/issues
Author: LLM.info Team
License: MIT
License-File: LICENSE
Keywords: ai,development,framework,mcp,spec-driven
Classifier: Development Status :: 5 - Production/Stable
Classifier: Intended Audience :: Developers
Classifier: Operating System :: OS Independent
Classifier: Programming Language :: Python :: 3
Classifier: Programming Language :: Python :: 3.10
Classifier: Programming Language :: Python :: 3.11
Classifier: Programming Language :: Python :: 3.12
Classifier: Programming Language :: Python :: 3.13
Classifier: Programming Language :: Python :: 3.14
Classifier: Topic :: Software Development :: Quality Assurance
Requires-Python: >=3.10
Requires-Dist: click>=8.0.0
Requires-Dist: jinja2>=3.0.0
Requires-Dist: packaging>=21.0
Requires-Dist: pyyaml>=6.0
Requires-Dist: questionary>=2.0.0
Requires-Dist: rich>=13.0.0
Provides-Extra: automation
Requires-Dist: google-generativeai>=0.3.0; extra == 'automation'
Requires-Dist: openai>=1.0.0; extra == 'automation'
Provides-Extra: dev
Requires-Dist: black>=24.0.0; extra == 'dev'
Requires-Dist: mypy>=1.10.0; extra == 'dev'
Requires-Dist: pip-audit>=2.6.0; extra == 'dev'
Requires-Dist: pytest-asyncio>=0.23.0; extra == 'dev'
Requires-Dist: pytest-cov>=5.0.0; extra == 'dev'
Requires-Dist: pytest>=8.0.0; extra == 'dev'
Requires-Dist: ruff>=0.5.0; extra == 'dev'
Requires-Dist: types-pyyaml>=6.0.0; extra == 'dev'
Provides-Extra: mcp
Requires-Dist: coverage>=7.0.0; extra == 'mcp'
Requires-Dist: mcp>=0.9.0; extra == 'mcp'
Provides-Extra: s3
Requires-Dist: boto3>=1.26.0; extra == 's3'
